odoo/addons/helpdesk_mgmt_merge/README.rst
odoo/addons/helpdesk_mgmt_merge/__init__.py
odoo/addons/helpdesk_mgmt_merge/__manifest__.py
odoo/addons/helpdesk_mgmt_merge/i18n/es.po
odoo/addons/helpdesk_mgmt_merge/i18n/helpdesk_mgmt_merge.pot
odoo/addons/helpdesk_mgmt_merge/i18n/it.po
odoo/addons/helpdesk_mgmt_merge/i18n/pt_BR.po
odoo/addons/helpdesk_mgmt_merge/readme/CONTRIBUTORS.md
odoo/addons/helpdesk_mgmt_merge/readme/DESCRIPTION.md
odoo/addons/helpdesk_mgmt_merge/readme/USAGE.md
odoo/addons/helpdesk_mgmt_merge/security/ir.model.access.csv
odoo/addons/helpdesk_mgmt_merge/static/description/icon.png
odoo/addons/helpdesk_mgmt_merge/static/description/index.html
odoo/addons/helpdesk_mgmt_merge/tests/__init__.py
odoo/addons/helpdesk_mgmt_merge/tests/test_helpdesk_mgmt_merge.py
odoo/addons/helpdesk_mgmt_merge/wizard/__init__.py
odoo/addons/helpdesk_mgmt_merge/wizard/helpdesk_ticket_merge.py
odoo/addons/helpdesk_mgmt_merge/wizard/helpdesk_ticket_merge_views.xml
odoo_addon_helpdesk_mgmt_merge-18.0.1.0.2.dist-info/METADATA
odoo_addon_helpdesk_mgmt_merge-18.0.1.0.2.dist-info/WHEEL
odoo_addon_helpdesk_mgmt_merge-18.0.1.0.2.dist-info/top_level.txt
odoo_addon_helpdesk_mgmt_merge-18.0.1.0.2.dist-info/RECORD
